hfilesize/__init__.py
hfilesize/hfilesize.py
siemkit/__init__.py
siemkit/adaptors.py
siemkit/cfg.py
siemkit/const.py
siemkit/csv.py
siemkit/data.py
siemkit/event.py
siemkit/file.py
siemkit/flag.py
siemkit/generate.py
siemkit/hash.py
siemkit/html.py
siemkit/ldap.py
siemkit/listen.py
siemkit/logging.py
siemkit/net.py
siemkit/parse.py
siemkit/random.py
siemkit/receive.py
siemkit/send.py
siemkit/smtp.py
siemkit/time.py
siemkit/web.py
siemkit/api/__init__.py
siemkit/api/arcsight.py
siemkit/api/arcsight/__init__.py
siemkit/api/arcsight/esm/__init__.py
siemkit/api/arcsight/esm/v72/__init__.py
siemkit/api/arcsight/esm/v72/activelist.py
siemkit/api/arcsight/esm/v72/auth.py
siemkit/api/arcsight/esm/v72/events.py
siemkit/arcsight/__init__.py
siemkit/simulate/__init__.py
siemkit/simulate/cef/__init__.py
siemkit/win32/__init__.py
siemkit/win32/registry.py
siemkit-0.0.17.dist-info/LICENSE
siemkit-0.0.17.dist-info/METADATA
siemkit-0.0.17.dist-info/NOTICE
siemkit-0.0.17.dist-info/WHEEL
siemkit-0.0.17.dist-info/top_level.txt
siemkit-0.0.17.dist-info/RECORD
